{
    "coffee":{
        "results": [
          {
            "fsq_id": "624266cdbeb69167d773e046",
            "categories": [
              {
                "id": 13032,
                "name": "Cafes, Coffee, and Tea Houses",
                "icon": {
                  "prefix": "https://ss3.4sqi.net/img/categories_v2/food/default_",
                  "suffix": ".png"
                }
              }
            ],
            "chains": [
              {
                "id": "f4261794-a1ea-47ae-a9a6-981b8965bcb1",
                "name": "Dutch Bros Coffee"
              }
            ],
            "distance": 3134,
            "geocodes": {
              "main": {
                "latitude": 36.055396,
                "longitude": -115.273929
              }
            },
            "link": "/v3/places/624266cdbeb69167d773e046",
            "location": {
              "address": "8295 W Warm Springs Rd",
              "census_block": "320030029761040",
              "country": "US",
              "cross_street": "",
              "dma": "Las Vegas",
              "formatted_address": "8295 W Warm Springs Rd, Las Vegas, NV 89113",
              "locality": "Las Vegas",
              "neighborhood": [
                "Spring Valley"
              ],
              "postcode": "89113",
              "region": "NV"
            },
            "name": "Dutch Bros Coffee",
            "related_places": {},
            "timezone": "America/Los_Angeles"
          },
          {
            "fsq_id": "50e07849e4b07dd5e2653ae1",
            "categories": [
              {
                "id": 13001,
                "name": "Bagel Shop",
                "icon": {
                  "prefix": "https://ss3.4sqi.net/img/categories_v2/food/bagels_",
                  "suffix": ".png"
                }
              }
            ],
            "chains": [
              {
                "id": "2cb519f8-883c-4263-860a-cd83325fbb97",
                "name": "Dunkin'"
              }
            ],
            "distance": 2849,
            "geocodes": {
              "main": {
                "latitude": 36.056767,
                "longitude": -115.27841
              }
            },
            "link": "/v3/places/50e07849e4b07dd5e2653ae1",
            "location": {
              "address": "7250 S Durango Dr",
              "address_extended": "Ste 100",
              "census_block": "320030029761038",
              "country": "US",
              "cross_street": "at W Warm Springs Rd",
              "dma": "Las Vegas",
              "formatted_address": "7250 S Durango Dr (at W Warm Springs Rd), Las Vegas, NV 89113",
              "locality": "Las Vegas",
              "neighborhood": [
                "Spring Valley"
              ],
              "postcode": "89113",
              "region": "NV"
            },
            "name": "Dunkin'",
            "related_places": {},
            "timezone": "America/Los_Angeles"
          },
          {
            "fsq_id": "5621337a498e1aa0a12d8763",
            "categories": [
              {
                "id": 13002,
                "name": "Bakery",
                "icon": {
                  "prefix": "https://ss3.4sqi.net/img/categories_v2/food/bakery_",
                  "suffix": ".png"
                }
              },
              {
                "id": 13043,
                "name": "Donut Shop",
                "icon": {
                  "prefix": "https://ss3.4sqi.net/img/categories_v2/food/donuts_",
                  "suffix": ".png"
                }
              },
              {
                "id": 13065,
                "name": "Restaurant",
                "icon": {
                  "prefix": "https://ss3.4sqi.net/img/categories_v2/food/default_",
                  "suffix": ".png"
                }
              }
            ],
            "chains": [],
            "distance": 3468,
            "geocodes": {
              "main": {
                "latitude": 36.069727,
                "longitude": -115.298442
              },
              "roof": {
                "latitude": 36.069727,
                "longitude": -115.298442
              }
            },
            "link": "/v3/places/5621337a498e1aa0a12d8763",
            "location": {
              "address": "6545 S Fort Apache Rd",
              "address_extended": "Ste 130",
              "census_block": "320030058691000",
              "country": "US",
              "cross_street": "at W Sunset Rd",
              "dma": "Las Vegas",
              "formatted_address": "6545 S Fort Apache Rd (at W Sunset Rd), Las Vegas, NV 89148",
              "locality": "Las Vegas",
              "neighborhood": [
                "Rhodes Ranch"
              ],
              "postcode": "89148",
              "region": "NV"
            },
            "name": "Glaze Doughnuts",
            "related_places": {},
            "timezone": "America/Los_Angeles"
          },
          {
            "fsq_id": "4b86e6fcf964a520e5a431e3",
            "categories": [
              {
                "id": 13059,
                "name": "Juice Bar",
                "icon": {
                  "prefix": "https://ss3.4sqi.net/img/categories_v2/food/juicebar_",
                  "suffix": ".png"
                }
              }
            ],
            "chains": [
              {
                "id": "2cd1878e-99c9-4d55-afbf-da408239814e",
                "name": "Tropical Smoothie Cafe"
              }
            ],
            "distance": 2581,
            "geocodes": {
              "main": {
                "latitude": 36.054594,
                "longitude": -115.279611
              },
              "roof": {
                "latitude": 36.054594,
                "longitude": -115.279611
              }
            },
            "link": "/v3/places/4b86e6fcf964a520e5a431e3",
            "location": {
              "address": "7375 S Durango Dr",
              "address_extended": "Ste 107",
              "census_block": "320030058551000",
              "country": "US",
              "cross_street": "at W Warm Springs Rd",
              "dma": "Las Vegas",
              "formatted_address": "7375 S Durango Dr (at W Warm Springs Rd), Las Vegas, NV 89113",
              "locality": "Las Vegas",
              "neighborhood": [
                "Rhodes Ranch"
              ],
              "postcode": "89113",
              "region": "NV"
            },
            "name": "Tropical Smoothie Cafe",
            "related_places": {},
            "timezone": "America/Los_Angeles"
          },
          {
            "fsq_id": "5a47c6fbc0f163205549429c",
            "categories": [
              {
                "id": 13034,
                "name": "Café",
                "icon": {
                  "prefix": "https://ss3.4sqi.net/img/categories_v2/food/cafe_",
                  "suffix": ".png"
                }
              },
              {
                "id": 13035,
                "name": "Coffee Shop",
                "icon": {
                  "prefix": "https://ss3.4sqi.net/img/categories_v2/food/coffeeshop_",
                  "suffix": ".png"
                }
              },
              {
                "id": 13068,
                "name": "American Restaurant",
                "icon": {
                  "prefix": "https://ss3.4sqi.net/img/categories_v2/food/default_",
                  "suffix": ".png"
                }
              }
            ],
            "chains": [],
            "distance": 4750,
            "geocodes": {
              "main": {
                "latitude": 36.081189,
                "longitude": -115.297109
              },
              "roof": {
                "latitude": 36.081189,
                "longitude": -115.297109
              }
            },
            "link": "/v3/places/5a47c6fbc0f163205549429c",
            "location": {
              "address": "5910 S Fort Apache Rd",
              "address_extended": "Ste 103",
              "census_block": "320030058601024",
              "country": "US",
              "cross_street": "",
              "dma": "Las Vegas",
              "formatted_address": "5910 S Fort Apache Rd, Las Vegas, NV 89148",
              "locality": "Las Vegas",
              "neighborhood": [
                "Spring Valley"
              ],
              "postcode": "89148",
              "region": "NV"
            },
            "name": "Neighbors",
            "related_places": {},
            "timezone": "America/Los_Angeles"
          }
        ],
        "context": {
          "geo_bounds": {
            "circle": {
              "center": {
                "latitude": 36.0385188,
                "longitude": -115.3005762
              },
              "radius": 22000
            }
          }
        }
      },
    "restaruants":{
        "results": [
          {
            "fsq_id": "4aa955c1f964a520235320e3",
            "categories": [
              {
                "id": 13065,
                "name": "Restaurant",
                "icon": {
                  "prefix": "https://ss3.4sqi.net/img/categories_v2/food/default_",
                  "suffix": ".png"
                }
              }
            ],
            "chains": [],
            "distance": 2040,
            "geocodes": {
              "main": {
                "latitude": 36.041889,
                "longitude": -115.278186
              },
              "roof": {
                "latitude": 36.041889,
                "longitude": -115.278186
              }
            },
            "link": "/v3/places/4aa955c1f964a520235320e3",
            "location": {
              "address": "8090 S Durango Dr",
              "address_extended": "Ste 103",
              "census_block": "320030029771007",
              "country": "US",
              "cross_street": "at W Windmill Ln",
              "dma": "Las Vegas",
              "formatted_address": "8090 S Durango Dr (at W Windmill Ln), Las Vegas, NV 89113",
              "locality": "Las Vegas",
              "neighborhood": [
                "Spring Valley"
              ],
              "postcode": "89113",
              "region": "NV"
            },
            "name": "Island Flavor",
            "related_places": {},
            "timezone": "America/Los_Angeles"
          },
          {
            "fsq_id": "542993df498e550c05c53401",
            "categories": [
              {
                "id": 13068,
                "name": "American Restaurant",
                "icon": {
                  "prefix": "https://ss3.4sqi.net/img/categories_v2/food/default_",
                  "suffix": ".png"
                }
              },
              {
                "id": 13314,
                "name": "New American Restaurant",
                "icon": {
                  "prefix": "https://ss3.4sqi.net/img/categories_v2/food/newamerican_",
                  "suffix": ".png"
                }
              }
            ],
            "chains": [],
            "distance": 2682,
            "geocodes": {
              "main": {
                "latitude": 36.05626,
                "longitude": -115.280618
              },
              "roof": {
                "latitude": 36.05626,
                "longitude": -115.280618
              }
            },
            "link": "/v3/places/542993df498e550c05c53401",
            "location": {
              "address": "8680 W Warm Springs Rd",
              "address_extended": "Ste 170",
              "census_block": "320030058591016",
              "country": "US",
              "cross_street": "at S Durango Dr",
              "dma": "Las Vegas",
              "formatted_address": "8680 W Warm Springs Rd (at S Durango Dr), Las Vegas, NV 89148",
              "locality": "Las Vegas",
              "neighborhood": [
                "Rhodes Ranch"
              ],
              "postcode": "89148",
              "region": "NV"
            },
            "name": "SkinnyFATS",
            "related_places": {
              "parent": {
                "fsq_id": "532cc2b7498edf9bb7288908",
                "name": "Orange Grove at Rhodes Ranch"
              },
              "children": []
            },
            "timezone": "America/Los_Angeles"
          },
          {
            "fsq_id": "4b84934df964a5207c3c31e3",
            "categories": [
              {
                "id": 13065,
                "name": "Restaurant",
                "icon": {
                  "prefix": "https://ss3.4sqi.net/img/categories_v2/food/default_",
                  "suffix": ".png"
                }
              }
            ],
            "chains": [],
            "distance": 2851,
            "geocodes": {
              "main": {
                "latitude": 36.055899,
                "longitude": -115.277268
              },
              "roof": {
                "latitude": 36.055899,
                "longitude": -115.277268
              }
            },
            "link": "/v3/places/4b84934df964a5207c3c31e3",
            "location": {
              "address": "8520 W Warm Springs Rd",
              "address_extended": "Ste 102",
              "census_block": "320030029761038",
              "country": "US",
              "cross_street": "btwn S Durango Dr & Gagnier Blvd",
              "dma": "Las Vegas",
              "formatted_address": "8520 W Warm Springs Rd (btwn S Durango Dr & Gagnier Blvd), Las Vegas, NV 89113",
              "locality": "Las Vegas",
              "neighborhood": [
                "Spring Valley"
              ],
              "postcode": "89113",
              "region": "NV"
            },
            "name": "Teriyaki Madness",
            "related_places": {},
            "timezone": "America/Los_Angeles"
          },
          {
            "fsq_id": "4b9accd3f964a520f2d635e3",
            "categories": [
              {
                "id": 13034,
                "name": "Café",
                "icon": {
                  "prefix": "https://ss3.4sqi.net/img/categories_v2/food/cafe_",
                  "suffix": ".png"
                }
              },
              {
                "id": 13148,
                "name": "French Restaurant",
                "icon": {
                  "prefix": "https://ss3.4sqi.net/img/categories_v2/food/french_",
                  "suffix": ".png"
                }
              },
              {
                "id": 13334,
                "name": "Sandwich Restaurant",
                "icon": {
                  "prefix": "https://ss3.4sqi.net/img/categories_v2/food/deli_",
                  "suffix": ".png"
                }
              }
            ],
            "chains": [],
            "distance": 3996,
            "geocodes": {
              "main": {
                "latitude": 36.066897,
                "longitude": -115.272948
              },
              "roof": {
                "latitude": 36.066897,
                "longitude": -115.272948
              }
            },
            "link": "/v3/places/4b9accd3f964a520f2d635e3",
            "location": {
              "address": "8359 W Sunset Rd",
              "address_extended": "Ste 100",
              "census_block": "320030029742019",
              "country": "US",
              "cross_street": "",
              "dma": "Las Vegas",
              "formatted_address": "8359 W Sunset Rd, Las Vegas, NV 89113",
              "locality": "Las Vegas",
              "neighborhood": [
                "Southwest Las Vegas"
              ],
              "postcode": "89113",
              "region": "NV"
            },
            "name": "Baguette Cafe",
            "related_places": {},
            "timezone": "America/Los_Angeles"
          },
          {
            "fsq_id": "4bcadd8ccc8cd13abe67becf",
            "categories": [
              {
                "id": 13003,
                "name": "Bar",
                "icon": {
                  "prefix": "https://ss3.4sqi.net/img/categories_v2/nightlife/pub_",
                  "suffix": ".png"
                }
              }
            ],
            "chains": [],
            "distance": 4827,
            "geocodes": {
              "main": {
                "latitude": 36.078724,
                "longitude": -115.279922
              },
              "roof": {
                "latitude": 36.078724,
                "longitude": -115.279922
              }
            },
            "link": "/v3/places/4bcadd8ccc8cd13abe67becf",
            "location": {
              "address": "6065 S Durango Dr",
              "census_block": "320030058601008",
              "country": "US",
              "cross_street": "at W Patrick Ln",
              "dma": "Las Vegas",
              "formatted_address": "6065 S Durango Dr (at W Patrick Ln), Las Vegas, NV 89113",
              "locality": "Las Vegas",
              "neighborhood": [
                "Southwest Las Vegas"
              ],
              "postcode": "89113",
              "region": "NV"
            },
            "name": "Giuseppe's Bar & Grille Las Vegas",
            "related_places": {},
            "timezone": "America/Los_Angeles"
          }
        ],
        "context": {
          "geo_bounds": {
            "circle": {
              "center": {
                "latitude": 36.0385188,
                "longitude": -115.3005762
              },
              "radius": 22000
            }
          }
        }
      },
    "hotel":{
        "results": [
          {
            "fsq_id": "5761edad498e4d7d511c2763",
            "categories": [
              {
                "id": 11073,
                "name": "Spa",
                "icon": {
                  "prefix": "https://ss3.4sqi.net/img/categories_v2/shops/spa_",
                  "suffix": ".png"
                }
              },
              {
                "id": 19014,
                "name": "Hotel",
                "icon": {
                  "prefix": "https://ss3.4sqi.net/img/categories_v2/travel/hotel_",
                  "suffix": ".png"
                }
              }
            ],
            "chains": [],
            "distance": 13491,
            "geocodes": {
              "main": {
                "latitude": 36.109546,
                "longitude": -115.178491
              },
              "roof": {
                "latitude": 36.109546,
                "longitude": -115.178491
              }
            },
            "link": "/v3/places/5761edad498e4d7d511c2763",
            "location": {
              "address": "2600 W Harmon Ave",
              "census_block": "320030067001011",
              "country": "US",
              "cross_street": "",
              "formatted_address": "2600 W Harmon Ave, Las Vegas, NV 89158",
              "locality": "Las Vegas",
              "neighborhood": [
                "Bracken"
              ],
              "postcode": "89158",
              "region": "NV"
            },
            "name": "Vdara Hotel & Spa",
            "related_places": {
              "children": [
                {
                  "fsq_id": "5c68cb1da92d98002c93e304",
                  "name": "Vdara Club Lounge"
                },
                {
                  "fsq_id": "4fca566ee4b026db02b8d609",
                  "name": "Vdara"
                },
                {
                  "fsq_id": "52d32635498e9ed7e7a43ff9",
                  "name": "Vdara Executive Suite"
                },
                {
                  "fsq_id": "4d5dba93d979ba7a5a4db4c7",
                  "name": "Market Cafe Vdara"
                },
                {
                  "fsq_id": "52a9d59011d2be2bc32b0025",
                  "name": "Starbucks"
                },
                {
                  "fsq_id": "4db880956a2334682d944fa3",
                  "name": "Vdara Hotel - Valet"
                },
                {
                  "fsq_id": "4d5dbad4d979ba7a5f4eb4c7",
                  "name": "Spa & Salon Vdara"
                },
                {
                  "fsq_id": "4b94899ff964a520c87c34e3",
                  "name": "Vice Versa Patio & Lounge"
                }
              ]
            },
            "timezone": "America/Los_Angeles"
          },
          {
            "fsq_id": "41326e00f964a520c0131fe3",
            "categories": [
              {
                "id": 19009,
                "name": "Lodging",
                "icon": {
                  "prefix": "https://ss3.4sqi.net/img/categories_v2/travel/default_",
                  "suffix": ".png"
                }
              }
            ],
            "chains": [],
            "distance": 13873,
            "geocodes": {
              "main": {
                "latitude": 36.112776,
                "longitude": -115.173925
              }
            },
            "link": "/v3/places/41326e00f964a520c0131fe3",
            "location": {
              "address": "3600 Las Vegas Blvd S",
              "census_block": "320030067001011",
              "country": "US",
              "cross_street": "at W Flamingo Rd",
              "dma": "Las Vegas",
              "formatted_address": "3600 Las Vegas Blvd S (at W Flamingo Rd), Las Vegas, NV 89109",
              "locality": "Las Vegas",
              "neighborhood": [
                "Bracken"
              ],
              "postcode": "89109",
              "region": "NV"
            },
            "name": "Bellagio Hotel and Casino",
            "related_places": {
              "children": [
                {
                  "fsq_id": "4ed94bc30e011b46ed0edde4",
                  "name": "Hermès"
                },
                {
                  "fsq_id": "4cc058eaca4aa1cd94661fb4",
                  "name": "Bellagio Ballroom 1"
                },
                {
                  "fsq_id": "4df3d97218386ecb4e320c11",
                  "name": "Bellagio Chapel"
                },
                {
                  "fsq_id": "4b48c400f964a520025626e3",
                  "name": "Snacks"
                },
                {
                  "fsq_id": "51ae0b6d498eca4db4bbfe39",
                  "name": "Gauguin 1"
                },
                {
                  "fsq_id": "46f7d99bf964a520044b1fe3",
                  "name": "Petrossian Bar & Lounge"
                },
                {
                  "fsq_id": "4e192c09b61c8f9ada538a3a",
                  "name": "Fendi"
                },
                {
                  "fsq_id": "4b46ac72f964a520a32626e3",
                  "name": "Michael Mina"
                },
                {
                  "fsq_id": "4cb4ddee8db0a143af5b5e16",
                  "name": "Poolside Bar at Bellagio"
                },
                {
                  "fsq_id": "50628b1ae4b058a95f7c755b",
                  "name": "Chanel"
                },
                {
                  "fsq_id": "4ad7ce2ef964a520f00e21e3",
                  "name": "The Buffet at Bellagio"
                },
                {
                  "fsq_id": "4d7f0998dd4a6ea83cca7325",
                  "name": "Prime Patio"
                },
                {
                  "fsq_id": "4a775b3df964a52042e41fe3",
                  "name": "Yellowtail"
                },
                {
                  "fsq_id": "5de5603b616eb40008dfa959",
                  "name": "Bellagio Ballroom 5"
                },
                {
                  "fsq_id": "4c2662bf905a0f47f1356360",
                  "name": "Mangia Employee Dining"
                },
                {
                  "fsq_id": "4d9541f92bd6f04d3d441b50",
                  "name": "Bellagio Parking Garage"
                },
                {
                  "fsq_id": "4d110db3b765224b40a8ee32",
                  "name": "Café Gelato Ice Cream and Sweets"
                },
                {
                  "fsq_id": "5b33dbcb82a750002c6ef0cf",
                  "name": "Spago by Wolfgang Puck"
                },
                {
                  "fsq_id": "4f6dfa10e4b0f577d26827b4",
                  "name": "Bellagio Pool Cafe And Deck"
                },
                {
                  "fsq_id": "4b329632f964a520530f25e3",
                  "name": "Palio"
                },
                {
                  "fsq_id": "4ab9bd6af964a5203b8020e3",
                  "name": "Prime Steakhouse"
                },
                {
                  "fsq_id": "4cb254b81463a143419faca9",
                  "name": "Gucci - The Shops at Via Bellagio"
                },
                {
                  "fsq_id": "4e8d64ff30f82b1224f80a1d",
                  "name": "Bellagio Employee Entrance"
                },
                {
                  "fsq_id": "4e9640a90aafdb60e06de625",
                  "name": "Tēsorīni"
                },
                {
                  "fsq_id": "4bd224e49854d13a9810fb4d",
                  "name": "Tuscany Kitchen"
                },
                {
                  "fsq_id": "4ad6ac07f964a5201e0821e3",
                  "name": "Noodles"
                },
                {
                  "fsq_id": "4b42b0f0f964a520ced825e3",
                  "name": "Picasso"
                },
                {
                  "fsq_id": "4bac256bf964a52024e73ae3",
                  "name": "Cirque Boutique"
                },
                {
                  "fsq_id": "50e8a4bde4b0b7b96ab816c1",
                  "name": "Bellagio Suites"
                },
                {
                  "fsq_id": "55330296498e17137cb5aeba",
                  "name": "Lago by Julian Serrano"
                },
                {
                  "fsq_id": "58a786a1fd27166ea4ccb9e4",
                  "name": "Starbucks"
                },
                {
                  "fsq_id": "4c55fda73e2220a19f873ba5",
                  "name": "Tutto"
                },
                {
                  "fsq_id": "519e3c31498e0532f891b0c4",
                  "name": "Bellagio Monet Conference Room"
                },
                {
                  "fsq_id": "4c252396f1272d7f824584c5",
                  "name": "Bellagio High Limit"
                },
                {
                  "fsq_id": "4c262cfe5c5ca593eb9c45fe",
                  "name": "Bellagio Employee Garage"
                },
                {
                  "fsq_id": "4aa4177bf964a5203e4520e3",
                  "name": "Bellagio Cypress Pools"
                },
                {
                  "fsq_id": "4aa49371f964a5201d4720e3",
                  "name": "Jasmine"
                },
                {
                  "fsq_id": "4a6de674f964a52048d31fe3",
                  "name": "FIX Restaurant & Bar"
                },
                {
                  "fsq_id": "4ed817ac61af8a14b387a0c2",
                  "name": "Bellagio Convention Center"
                },
                {
                  "fsq_id": "4d530283dcce224b1892f21b",
                  "name": "Corporate Channel Management Offices - Bellagio Hotel & Casino"
                },
                {
                  "fsq_id": "4c89c3a82e3337043005be41",
                  "name": "Chihuly Sculpture - Fiori Di Como"
                },
                {
                  "fsq_id": "4c2e55a566e40f47b909c08b",
                  "name": "Giardini Garden Store"
                },
                {
                  "fsq_id": "5bf08c0789b06a002c50b294",
                  "name": "Bellagio Gallery of Fine Art"
                },
                {
                  "fsq_id": "4ab0498ef964a520dd6620e3",
                  "name": "Fountains of Bellagio"
                },
                {
                  "fsq_id": "563be50acd103864def2d1cf",
                  "name": "Winston, Harry: Harry Winston"
                },
                {
                  "fsq_id": "4d2216e15acaa35d1771d535",
                  "name": "Bellagio North Valet"
                },
                {
                  "fsq_id": "50a8918fe4b0ee89d00d1bcb",
                  "name": "Yellowtail - Bellagio Hotel"
                },
                {
                  "fsq_id": "50f6121ae4b0d373e125d280",
                  "name": "Bellagio West Wing"
                },
                {
                  "fsq_id": "4c436d96429a0f479a5d471e",
                  "name": "Bellagio VIP Lounge"
                },
                {
                  "fsq_id": "4eb03ddb4690488dac0a4071",
                  "name": "Bellagio Towers"
                },
                {
                  "fsq_id": "4b5a20eef964a52005af28e3",
                  "name": "Chanel"
                },
                {
                  "fsq_id": "41326e00f964a520a5131fe3",
                  "name": "Allegro Lounge"
                },
                {
                  "fsq_id": "4b4c154af964a52012ae26e3",
                  "name": "ARIA Express Bellagio Station"
                },
                {
                  "fsq_id": "4dbeca17cda109aa6cd1dcaa",
                  "name": "Raphael Room- Bellagio Convention Center"
                },
                {
                  "fsq_id": "4e1f2d86d4c0fc6e34401980",
                  "name": "Cypress Premier Lounges at the Bellagio Pool"
                },
                {
                  "fsq_id": "5ad283f6eb449939d8d4d7ba",
                  "name": "Bellagio Patisserie"
                },
                {
                  "fsq_id": "4d2a8ab7b818a35d098ba88a",
                  "name": "Main Cage"
                },
                {
                  "fsq_id": "526a02d3498e8131cd0141c5",
                  "name": "Platino"
                },
                {
                  "fsq_id": "50cd114fe4b0c490c37db456",
                  "name": "Bellagio Tower 5"
                },
                {
                  "fsq_id": "4c127f9382a3c9b675d5f9f8",
                  "name": "Essentials"
                },
                {
                  "fsq_id": "5bcd4717ccad6b002ca4840d",
                  "name": "O Theater"
                },
                {
                  "fsq_id": "527db01811d28ec6bffe85c7",
                  "name": "World's Largest Chocolate Fountain"
                },
                {
                  "fsq_id": "4b0afb62f964a520132b23e3",
                  "name": "Bellagio Spa & Salon"
                },
                {
                  "fsq_id": "41326e00f964a520ad131fe3",
                  "name": "Baccarat Bar"
                },
                {
                  "fsq_id": "4b4a7c88f964a5200d8926e3",
                  "name": "Bellagio Race And Sports Book"
                },
                {
                  "fsq_id": "4fe1efaa0cd6f12db8a28d5b",
                  "name": "Avis Rent A Car"
                },
                {
                  "fsq_id": "5069da65e4b0c7c0534a5b49",
                  "name": "Gauguin"
                },
                {
                  "fsq_id": "4c40510e3735be9a079b16a4",
                  "name": "Bellagio Banquet Office"
                },
                {
                  "fsq_id": "4e9756a1b803b3436f170e2a",
                  "name": "Bell Tower at Bellagio"
                },
                {
                  "fsq_id": "4c1533f4a9c220a1eec3589d",
                  "name": "Bellagio Wedding Chapels"
                },
                {
                  "fsq_id": "4d5dc4a2b6b9a1cdb6dc5a51",
                  "name": "Bellagio Business Center"
                },
                {
                  "fsq_id": "4b3e46adf964a520899a25e3",
                  "name": "Le Cirque"
                },
                {
                  "fsq_id": "59c6ed94e1f0aa4b92dd3d72",
                  "name": "SJP by Sarah Jessica Parker"
                },
                {
                  "fsq_id": "5ad52c0d0f013c06bf157522",
                  "name": "Juice Press"
                },
                {
                  "fsq_id": "4aff3365f964a520d53522e3",
                  "name": "Conservatory & Botanical Garden - Temporarily"
                },
                {
                  "fsq_id": "4cd5e1e5886cb60c05d38689",
                  "name": "Terrazza Di Sogno Las Vegas"
                },
                {
                  "fsq_id": "5e0d6541cbf5c90008c5e470",
                  "name": "The Mayfair Supper Club"
                },
                {
                  "fsq_id": "4cae5e4e1168a09376011a23",
                  "name": "Fitness Center"
                },
                {
                  "fsq_id": "502548a8e4b07a020e0d338a",
                  "name": "Bellagio V.I.P. Pool"
                },
                {
                  "fsq_id": "4eb4b14a61af0dda900bd8f8",
                  "name": "Lily Bar & Lounge"
                },
                {
                  "fsq_id": "5b7f2988dab4b1002cc23cda",
                  "name": "Sadelle's"
                },
                {
                  "fsq_id": "59eed5d5b2958f75247f7dfc",
                  "name": "Harvest"
                },
                {
                  "fsq_id": "4de1c42345dd180ae537856b",
                  "name": "Project h2o"
                },
                {
                  "fsq_id": "4cc637f1c844721e92baf301",
                  "name": "Bellagio Grand Ballroom"
                },
                {
                  "fsq_id": "4fbfb565e4b099ce1679a2eb",
                  "name": "Bellagio Spa Tower"
                },
                {
                  "fsq_id": "4c1f034c8b3aa593a0f09c5f",
                  "name": "O Theatre At Bellagio"
                },
                {
                  "fsq_id": "4f32bb0519836c91c7f43b0b",
                  "name": "Arcade"
                }
              ]
            },
            "timezone": "America/Los_Angeles"
          },
          {
            "fsq_id": "4b0e4cbdf964a520a85623e3",
            "categories": [
              {
                "id": 19014,
                "name": "Hotel",
                "icon": {
                  "prefix": "https://ss3.4sqi.net/img/categories_v2/travel/hotel_",
                  "suffix": ".png"
                }
              }
            ],
            "chains": [
              {
                "id": "89b696db-e6ea-419b-a129-59ca888ef0ce",
                "name": "Staybridge Suites"
              }
            ],
            "distance": 11750,
            "geocodes": {
              "main": {
                "latitude": 36.085421,
                "longitude": -115.183455
              },
              "roof": {
                "latitude": 36.085421,
                "longitude": -115.183455
              }
            },
            "link": "/v3/places/4b0e4cbdf964a520a85623e3",
            "location": {
              "address": "5735 Dean Martin Dr",
              "census_block": "320030029621086",
              "country": "US",
              "cross_street": "",
              "dma": "Las Vegas",
              "formatted_address": "5735 Dean Martin Dr, Las Vegas, NV 89118",
              "locality": "Las Vegas",
              "neighborhood": [
                "Boulder Junction"
              ],
              "postcode": "89118",
              "region": "NV"
            },
            "name": "Staybridge Suites Las Vegas, an IHG Hotel",
            "related_places": {},
            "timezone": "America/Los_Angeles"
          },
          {
            "fsq_id": "41326e00f964a520b2141fe3",
            "categories": [
              {
                "id": 19014,
                "name": "Hotel",
                "icon": {
                  "prefix": "https://ss3.4sqi.net/img/categories_v2/travel/hotel_",
                  "suffix": ".png"
                }
              }
            ],
            "chains": [
              {
                "id": "07244e20-c038-4873-8a4f-4124919d3f1b",
                "name": "Hyatt"
              }
            ],
            "distance": 13359,
            "geocodes": {
              "main": {
                "latitude": 36.102178,
                "longitude": -115.174401
              },
              "roof": {
                "latitude": 36.102178,
                "longitude": -115.174401
              }
            },
            "link": "/v3/places/41326e00f964a520b2141fe3",
            "location": {
              "address": "3790 Las Vegas Blvd S",
              "address_extended": "Apt 16A",
              "census_block": "320030067001022",
              "country": "US",
              "cross_street": "at W Tropicana Ave",
              "dma": "Las Vegas",
              "formatted_address": "3790 Las Vegas Blvd S (at W Tropicana Ave), Las Vegas, NV 89109",
              "locality": "Las Vegas",
              "neighborhood": [
                "Bracken"
              ],
              "postcode": "89109",
              "region": "NV"
            },
            "name": "New York-New York Hotel & Casino",
            "related_places": {
              "children": [
                {
                  "fsq_id": "4b5f1beff964a52091a629e3",
                  "name": "New York-New York"
                },
                {
                  "fsq_id": "4f91e61ce4b020a51dd7f88c",
                  "name": "High Limit Bar"
                },
                {
                  "fsq_id": "4b206800f964a520e63124e3",
                  "name": "Chin Chin"
                },
                {
                  "fsq_id": "4a4457f4f964a52079a71fe3",
                  "name": "Pour 24"
                },
                {
                  "fsq_id": "4afbb7a1f964a520031f22e3",
                  "name": "America"
                },
                {
                  "fsq_id": "4a70e3c2f964a520b3d81fe3",
                  "name": "Zumanity"
                },
                {
                  "fsq_id": "4cafb38fef1b3704bdb93400",
                  "name": "New York-New York Parking Garage"
                },
                {
                  "fsq_id": "4b4ab981f964a520938d26e3",
                  "name": "Broadway Burger Bar and Grill"
                },
                {
                  "fsq_id": "4d55da94fb65236a0168feb3",
                  "name": "New York Pizzeria"
                },
                {
                  "fsq_id": "4a975a2df964a520742920e3",
                  "name": "Il Fornaio"
                },
                {
                  "fsq_id": "4cc4824dc844721e94c1e901",
                  "name": "Las Vegas Harley-Davidson Shop"
                },
                {
                  "fsq_id": "4dc57135e4cd169dc64c58f9",
                  "name": "New York-New York Meeting Rooms"
                },
                {
                  "fsq_id": "4f543002e4b0b5d9df72f74c",
                  "name": "Greenwich Village Coffee Co."
                },
                {
                  "fsq_id": "52db7be6498e66c017221e39",
                  "name": "48th and Crepe"
                },
                {
                  "fsq_id": "49de8d02f964a52081601fe3",
                  "name": "Bar at Times Square"
                },
                {
                  "fsq_id": "4b96878bf964a5206ed234e3",
                  "name": "The Roller Coaster at New York-New York"
                },
                {
                  "fsq_id": "5da8ceba8969520008a4b74d",
                  "name": "The Big Apple Coaster & Arcade"
                },
                {
                  "fsq_id": "41326e00f964a52006141fe3",
                  "name": "Coyote Ugly"
                },
                {
                  "fsq_id": "41326e00f964a520b7141fe3",
                  "name": "Nine Fine Irishmen"
                },
                {
                  "fsq_id": "54a302ca498e3a87330a606b",
                  "name": "Tom's Urban Las Vegas"
                },
                {
                  "fsq_id": "4b1b998af964a52023fc23e3",
                  "name": "Nathan's Hot Dogs"
                },
                {
                  "fsq_id": "4c0a2879340720a1bdf48593",
                  "name": "Statue of Liberty"
                },
                {
                  "fsq_id": "54886091498ed3ea78f45386",
                  "name": "Shake Shack"
                },
                {
                  "fsq_id": "50fa145de4b02fe304efa1d5",
                  "name": "New York-New York Walkway to Excalibur"
                },
                {
                  "fsq_id": "5ad7a6e5e96d0c205a260c59",
                  "name": "Village Street Eateries"
                },
                {
                  "fsq_id": "59838cb3ad1ea40bd668c568",
                  "name": "Boat House Bar"
                },
                {
                  "fsq_id": "4ce3060e438b224bbd1280a3",
                  "name": "Brooklyn Bridge"
                },
                {
                  "fsq_id": "4a92b8b8f964a5206e1d20e3",
                  "name": "The Roller Coaster"
                },
                {
                  "fsq_id": "538699bd498e73b89178e1c6",
                  "name": "Hershey's Chocolate World"
                },
                {
                  "fsq_id": "4b820debf964a52032c930e3",
                  "name": "New York New York Sports Book"
                },
                {
                  "fsq_id": "4b843d1af964a520a52931e3",
                  "name": "Sirrico's Pizza"
                },
                {
                  "fsq_id": "4a347848f964a520499c1fe3",
                  "name": "Gonzalez Y Gonzalez"
                }
              ]
            },
            "timezone": "America/Los_Angeles"
          },
          {
            "fsq_id": "4f303f4ee4b062ad2df5cab1",
            "categories": [
              {
                "id": 10008,
                "name": "Casino",
                "icon": {
                  "prefix": "https://ss3.4sqi.net/img/categories_v2/arts_entertainment/casino_",
                  "suffix": ".png"
                }
              },
              {
                "id": 19014,
                "name": "Hotel",
                "icon": {
                  "prefix": "https://ss3.4sqi.net/img/categories_v2/travel/hotel_",
                  "suffix": ".png"
                }
              },
              {
                "id": 19018,
                "name": "Resort",
                "icon": {
                  "prefix": "https://ss3.4sqi.net/img/categories_v2/travel/resort_",
                  "suffix": ".png"
                }
              }
            ],
            "chains": [],
            "distance": 14124,
            "geocodes": {
              "main": {
                "latitude": 36.108816,
                "longitude": -115.169378
              },
              "roof": {
                "latitude": 36.108816,
                "longitude": -115.169378
              }
            },
            "link": "/v3/places/4f303f4ee4b062ad2df5cab1",
            "location": {
              "address": "80 E Harmon Ave",
              "census_block": "320030067001018",
              "country": "US",
              "cross_street": "btwn Audrie St & S Las Vegas Blvd",
              "dma": "Las Vegas",
              "formatted_address": "80 E Harmon Ave (btwn Audrie St & S Las Vegas Blvd), Las Vegas, NV 89109",
              "locality": "Las Vegas",
              "neighborhood": [
                "Bracken"
              ],
              "postcode": "89109",
              "region": "NV"
            },
            "name": "Elara, a Hilton Grand Vacations Hotel",
            "related_places": {
              "children": [
                {
                  "fsq_id": "520e449011d2d0313006439f",
                  "name": "Starbucks"
                },
                {
                  "fsq_id": "4c1d0416b9f876b027d97c46",
                  "name": "Elara Pool"
                },
                {
                  "fsq_id": "5019d6eae4b004b505599b36",
                  "name": "Elara Lobby Lounge"
                },
                {
                  "fsq_id": "4f955733e4b05b20f1f00e68",
                  "name": "Elara Fitness Center, Las Vegas Strip"
                },
                {
                  "fsq_id": "52f53eb5498e6b97eea6744f",
                  "name": "55th floor 4 bedroom penthouse Suite in Elara Hilton for 12"
                }
              ]
            },
            "timezone": "America/Los_Angeles"
          }
        ],
        "context": {
          "geo_bounds": {
            "circle": {
              "center": {
                "latitude": 36.0385188,
                "longitude": -115.3005762
              },
              "radius": 22000
            }
          }
        }
      },
    "market":{
        "results": [
          {
            "fsq_id": "4e26db4745ddb79afc652002",
            "categories": [
              {
                "id": 17043,
                "name": "Clothing Store",
                "icon": {
                  "prefix": "https://ss3.4sqi.net/img/categories_v2/shops/apparel_",
                  "suffix": ".png"
                }
              }
            ],
            "chains": [
              {
                "id": "4a5da2bc-82c7-4335-b165-e16b44e26e17",
                "name": "Banana Republic"
              }
            ],
            "distance": 11875,
            "geocodes": {
              "main": {
                "latitude": 36.053692,
                "longitude": -115.169744
              },
              "roof": {
                "latitude": 36.053692,
                "longitude": -115.169744
              }
            },
            "link": "/v3/places/4e26db4745ddb79afc652002",
            "location": {
              "address": "7400 Las Vegas Blvd S",
              "address_extended": "Ste 41",
              "census_block": "320030028371007",
              "country": "US",
              "cross_street": "",
              "dma": "Las Vegas",
              "formatted_address": "7400 Las Vegas Blvd S, Las Vegas, NV 89123",
              "locality": "Las Vegas",
              "neighborhood": [
                "Boulder Junction"
              ],
              "postcode": "89123",
              "region": "NV"
            },
            "name": "Banana Republic Factory Store",
            "related_places": {
              "parent": {
                "fsq_id": "4b3a574ff964a520196525e3",
                "name": "Las Vegas Premium Outlets - South"
              }
            },
            "timezone": "America/Los_Angeles"
          },
          {
            "fsq_id": "4f8b32a8e4b0202c07e37a42",
            "categories": [
              {
                "id": 17082,
                "name": "Furniture and Home Store",
                "icon": {
                  "prefix": "https://ss3.4sqi.net/img/categories_v2/shops/furniture_",
                  "suffix": ".png"
                }
              }
            ],
            "chains": [
              {
                "id": "51d0ad75-6341-4b18-9344-63dcff3795cc",
                "name": "The Container Store"
              }
            ],
            "distance": 11826,
            "geocodes": {
              "main": {
                "latitude": 36.068577,
                "longitude": -115.174347
              },
              "roof": {
                "latitude": 36.068577,
                "longitude": -115.174347
              }
            },
            "link": "/v3/places/4f8b32a8e4b0202c07e37a42",
            "location": {
              "address": "6521 Las Vegas Blvd S",
              "census_block": "320030028471022",
              "country": "US",
              "cross_street": "",
              "dma": "Las Vegas",
              "formatted_address": "6521 Las Vegas Blvd S, Las Vegas, NV 89119",
              "locality": "Las Vegas",
              "neighborhood": [
                "Boulder Junction"
              ],
              "postcode": "89119",
              "region": "NV"
            },
            "name": "The Container Store",
            "related_places": {
              "parent": {
                "fsq_id": "4a6cf730f964a52037d21fe3",
                "name": "Town Square Las Vegas"
              }
            },
            "timezone": "America/Los_Angeles"
          },
          {
            "fsq_id": "5c1c166331ac6c0039bf6adc",
            "categories": [
              {
                "id": 11163,
                "name": "Shipping, Freight, and Material Transportation Service",
                "icon": {
                  "prefix": "https://ss3.4sqi.net/img/categories_v2/shops/default_",
                  "suffix": ".png"
                }
              }
            ],
            "chains": [
              {
                "id": "ab4b13e0-d68a-012e-5619-003048cad9da",
                "name": "The UPS Store"
              }
            ],
            "distance": 3458,
            "geocodes": {
              "main": {
                "latitude": 36.069694,
                "longitude": -115.298369
              },
              "roof": {
                "latitude": 36.069694,
                "longitude": -115.298369
              }
            },
            "link": "/v3/places/5c1c166331ac6c0039bf6adc",
            "location": {
              "address": "6545 S Fort Apache Rd",
              "address_extended": "Ste 135",
              "census_block": "320030058691000",
              "country": "US",
              "cross_street": "",
              "dma": "Las Vegas",
              "formatted_address": "6545 S Fort Apache Rd, Las Vegas, NV 89148",
              "locality": "Las Vegas",
              "neighborhood": [
                "Rhodes Ranch"
              ],
              "postcode": "89148",
              "region": "NV"
            },
            "name": "The UPS Store",
            "related_places": {},
            "timezone": "America/Los_Angeles"
          },
          {
            "fsq_id": "5aa0c78997cf5a1b3ffe1679",
            "categories": [
              {
                "id": 11163,
                "name": "Shipping, Freight, and Material Transportation Service",
                "icon": {
                  "prefix": "https://ss3.4sqi.net/img/categories_v2/shops/default_",
                  "suffix": ".png"
                }
              }
            ],
            "chains": [
              {
                "id": "ab4b13e0-d68a-012e-5619-003048cad9da",
                "name": "The UPS Store"
              }
            ],
            "distance": 3872,
            "geocodes": {
              "main": {
                "latitude": 36.018348,
                "longitude": -115.265263
              },
              "roof": {
                "latitude": 36.018348,
                "longitude": -115.265263
              }
            },
            "link": "/v3/places/5aa0c78997cf5a1b3ffe1679",
            "location": {
              "address": "7995 Blue Diamond Rd",
              "address_extended": "Ste 102",
              "census_block": "320030058301002",
              "country": "US",
              "cross_street": "",
              "dma": "Las Vegas",
              "formatted_address": "7995 Blue Diamond Rd, Las Vegas, NV 89178",
              "locality": "Las Vegas",
              "postcode": "89178",
              "region": "NV"
            },
            "name": "The UPS Store",
            "related_places": {},
            "timezone": "America/Los_Angeles"
          },
          {
            "fsq_id": "4c069d318b4520a1a6ac8597",
            "categories": [
              {
                "id": 11163,
                "name": "Shipping, Freight, and Material Transportation Service",
                "icon": {
                  "prefix": "https://ss3.4sqi.net/img/categories_v2/shops/default_",
                  "suffix": ".png"
                }
              }
            ],
            "chains": [
              {
                "id": "ab4b13e0-d68a-012e-5619-003048cad9da",
                "name": "The UPS Store"
              }
            ],
            "distance": 5304,
            "geocodes": {
              "main": {
                "latitude": 36.043217,
                "longitude": -115.241874
              },
              "roof": {
                "latitude": 36.043217,
                "longitude": -115.241874
              }
            },
            "link": "/v3/places/4c069d318b4520a1a6ac8597",
            "location": {
              "address": "8020 S Rainbow Blvd",
              "address_extended": "Ste 100",
              "census_block": "320030029822005",
              "country": "US",
              "cross_street": "",
              "dma": "Las Vegas",
              "formatted_address": "8020 S Rainbow Blvd, Las Vegas, NV 89139",
              "locality": "Las Vegas",
              "postcode": "89139",
              "region": "NV"
            },
            "name": "The UPS Store",
            "related_places": {
              "parent": {
                "fsq_id": "501485c2e4b0f8ec78a5cc0d",
                "name": "Southwest Marketplace"
              }
            },
            "timezone": "America/Los_Angeles"
          }
        ],
        "context": {
          "geo_bounds": {
            "circle": {
              "center": {
                "latitude": 36.0385188,
                "longitude": -115.3005762
              },
              "radius": 22000
            }
          }
        }
      }
    }
